{
  "tag_heading": "na",
  "tag_public_url": "https://www.hilti.com/c/CLS_POWER_TOOL_INSERT_7126/CLS_INSERTS_PRESSING_CC_7126/r8824374",
  "content": "Cable cutter blade kits Self-service replacement blade kits for cordless cable cutting tools ### Categories: Home > Products > Tool inserts > Inserts for pressing, crimping & cutting ### FEATURES:Features Self-service replacement blade kits for ACSR and guy wire cutter Helps to keep your cordless cutting tools performing at their best, without the inconvenience of sending them away to a service center Applications Exchanging Cu/Al and ACSR blades for NUN 54-A cordless cutter Exchanging ACSR blades for NCT 25-A ACSR and guy wire cutter ### TECHNICAL DATA: ### ITEMS- 2172837 - Blade NBK 054 CUAL kit - Package Size 1 pc Package Contents: - 1x NBK 054 CUAL Blade kit - 2172836 - Blade NBK 054 ACSR kit - Package Size 1 pc Package Contents: - 1x NBK 054 ACSR Blade kit - 2187847 - Blade NBK IS 025 kit - Package Size 1 pc Package Contents: - 1x NBK IS 025 Blade - 2256713 - Blade NBK 45 S-22 kit - Package Size 1 pc Package Contents: - 1x Kit NCT45 Gen2 Blade",
  "tag_name": "Cable cutter blade kits",
  "tag_description": "Self-service replacement blade kits for cordless cable cutting tools",
  "tag_source": "HOL: Products",
  "tag_author": "na",
  "tag_created_at": "na",
  "tag_ingestion_date": "2025-05-21T13:11:22.112521",
  "tag_categories_leaf": "Inserts for pressing, crimping & cutting",
  "tag_categories_branch": "Home > Products > Tool inserts > Inserts for pressing, crimping & cutting",
  "tag_item_numbers": "['2172837', '2172836', '2187847', '2256713']",
  "tag_related_files": "[]",
  "tag_sidelinks": "na",
  "tag_language": "en",
  "tag_country": "us",
  "tag_keywords": "na",
  "tag_page_number": "na",
  "tag_sku": "r8824374",
  "tag_file_type": "product_page",
  "tag_file_extension": "html"
}