{
  "tag_heading": "na",
  "tag_public_url": "https://www.hilti.com/c/CLS_FIRESTOP_PROTECTION_7131/CLS_FIRESTOP_SEALANTS_SPRAY_7131/r4754117",
  "content": "CP- 605 Bottom-of-wall firestop sealant Low-shrinkage and easy-to-dispense firestop sealant for fire-rated and non-rated bottom of walls ### Categories: Home > Products > Firestop & fire protection > Sealants, sprays and coatings- - - ### FEATURES:Features Odorless – ideal for occupied buildings such as hospitals, schools, airports, etc. Soft foil packaging – reduces waste compared to hard cartridges Contains no hazardous ingredients listed in Prop 65 – also MEP-free and DINP-free (phthalate-containing substances) Low shrinkage (< 25%) according to ASTM C 1241 Applications Sealing bottom-of-wall joints in approved fire-rated assemblies For approval or certificate information, please see individual items. ### TECHNICAL DATA: LEED VOC: 43.21 g/l Base materials: Concrete, Drywall, Masonry, Metal Application temperature range: 35 - 104 °F Technical Data | LEED VOC | 43.21 g/l | Base materials | Concrete, Drywall, Masonry, Metal | Application temperature range | 35 - 104 °F | Approx. cure time | 3 mm/3 days | 1 | Can be painted | Yes | Product Class | Ultimate | Color | White | at 75°F/24°C, 50% relative humidity ### ITEMS- 2123410 - Bottom of Wall Sealant CP 605 580ml - Package Size 20 pc - 3544905 - CP605 bottom of wall - pallet - Package Size 1 pc Package Contents: - 600x Bottom of Wall Sealant CP 605 580ml",
  "tag_name": "CP- 605 Bottom-of-wall firestop sealant",
  "tag_description": "Low-shrinkage and easy-to-dispense firestop sealant for fire-rated and non-rated bottom of walls",
  "tag_source": "HOL: Products",
  "tag_author": "na",
  "tag_created_at": "na",
  "tag_ingestion_date": "2025-05-20T12:00:21.299706",
  "tag_categories_leaf": "Sealants, sprays and coatings",
  "tag_categories_branch": "Home > Products > Firestop & fire protection > Sealants, sprays and coatings",
  "tag_item_numbers": "['2123410', '3544905']",
  "tag_related_files": "[{'category': 'Technical information', 'url': 'https://productdata.hilti.com/APQ_HC_RAW/ASSET_DOC_LOC_5121303.pdf', 'description': 'Download Product Data Sheet (US_CA_ENG) for CP 605 Bottom-of-Wall Firestop Sealant'}, {'category': 'Technical information', 'url': 'https://productdata.hilti.com/APQ_HC_RAW/ASSET_DOC_LOC_6043115.pdf', 'description': 'Download Mold and Mildew Resistant Hilti Firestop Solutions'}, {'category': 'Schematic', 'url': 'https://productdata.hilti.com/APQ_HC_RAW/ASSET_DOC_LOC_11123636.pdf', 'description': 'Download LEEDv4.1 (CDPH) Emissions & VOC (SCAQMD-Rule 1113) Content Report_CP 605'}, {'category': 'Schematic', 'url': 'https://productdata.hilti.com/APQ_HC_RAW/ASSET_DOC_LOC_13694570.pdf', 'description': 'Download Green Building Materials Certification Form V5.0_2024'}, {'category': 'Certificate', 'url': 'https://productdata.hilti.com/APQ_HC_RAW/ASSET_DOC_LOC_4707997.pdf', 'description': 'Download UL Certificate of Compliance for CP 605 Bottom of Wall Firestop Sealant'}, {'category': 'Approval document', 'url': 'https://productdata.hilti.com/APQ_HC_RAW/ASSET_DOC_LOC_12947823.pdf', 'description': 'Download CPVC Compatibility Letter_August 2020'}, {'category': 'Test Report', 'url': 'https://productdata.hilti.com/APQ_HC_RAW/ASSET_DOC_LOC_5121585.pdf', 'description': 'Download Test Report (STC) for CP 605 Bottom-of-Wall Firestop Sealant'}, {'category': 'Material safety datasheet', 'url': 'https://productdata.hilti.com/APQ_HC_RAW/IBD_WWI-00000000000005930190_000.pdf', 'description': 'Download Material safety datasheet CP 605 (ES)'}, {'category': 'Material safety datasheet', 'url': 'https://productdata.hilti.com/APQ_HC_RAW/IBD_WWI-00000000000005930191_000.pdf', 'description': 'Download Material safety datasheet CP 605 (EN)'}, {'category': 'Sustainability Documentation', 'url': 'https://productdata.hilti.com/APQ_HC_RAW/SUS_5851155_000.pdf', 'description': 'Download  VOC_LEED_CDPH_CP 605_EN'}, {'category': 'Instruction for use', 'url': 'https://productdata.hilti.com/APQ_HC_RAW/PUB_5239470_000.pdf', 'description': 'Download Instruction for use CP 605'}]",
  "tag_sidelinks": "na",
  "tag_language": "en",
  "tag_country": "us",
  "tag_keywords": "na",
  "tag_page_number": "na",
  "tag_sku": "r4754117",
  "tag_file_type": "product_page",
  "tag_file_extension": "html"
}