{
  "tag_heading": "na",
  "tag_public_url": "https://www.hilti.com/c/CLS_POWER_TOOLS_7125/CLS_TOOLS_7125/CLS_ACC_SPECIALTY_POWER_TOOLS_7125/2243478",
  "content": "Cutter blade SSH CX (2) stnls. ### Categories: Home > Products > Power tools > Accessories for tools > Accessories for specialty power tools- - ### FEATURES:Features Help to keep your power shears operating at their best Simplify routine maintenance to help prolong the tools lifespan Applications Replacing wear parts used by Hilti cordless metal shears Expanding the range of applications possible with Hilti cordless metal shears ### TECHNICAL DATA: Product information: Designed for straight cuts in stainless steel up to 1.5mm (.06”) thick Additional Accessory Information: For cutting stainless steel with the SSH 6-A22 Technical Data | Product information | Designed for straight cuts in stainless steel up to 1.5mm (.06”) thick | Additional Accessory Information | For cutting stainless steel with the SSH 6-A22 ### ITEMS- 2243478 - Cutter blade SSH CX (2) stnls. - Package Size 2 pc",
  "tag_name": "Cutter blade SSH CX (2) stnls.",
  "tag_description": "",
  "tag_source": "HOL: Products",
  "tag_author": "na",
  "tag_created_at": "na",
  "tag_ingestion_date": "2025-05-21T10:04:51.000742",
  "tag_categories_leaf": "Accessories for specialty power tools",
  "tag_categories_branch": "Home > Products > Power tools > Accessories for tools > Accessories for specialty power tools",
  "tag_item_numbers": "['2243478']",
  "tag_related_files": "[]",
  "tag_sidelinks": "na",
  "tag_language": "en",
  "tag_country": "us",
  "tag_keywords": "na",
  "tag_page_number": "na",
  "tag_sku": "2243478",
  "tag_file_type": "product_page",
  "tag_file_extension": "html"
}