{
  "tag_heading": "na",
  "tag_public_url": "https://www.hilti.com/c/CLS_POWER_TOOL_INSERT_7126/CLS_METAL_N_WOOD_DRILL_BIT_7126/r1697732",
  "content": "HSS G Drill bit Premium HSS ground drill bit for drilling small holes in metal, DIN 338 compliant ### Categories: Home > Products > Tool inserts > Metal, wood and other material drill bits- - - ### FEATURES:Features Specially designed tip with split point for precise self-centering Fast start due to sharp 135-degree tip angle Spiral flute enabling easy chip removal, optimal application of lubricant to the drill bit tip and reduced heat generation Designed to get the maximum performance out of cordless tools – so you get more work done per battery charge Applications Drilling in unalloyed and medium-alloyed steel ### TECHNICAL DATA: Product Class: Premium Connection end: Smooth shank Material composition: HSS M2 Technical Data | Product Class | Premium | Connection end | Smooth shank | Material composition | HSS M2 | DIN | DIN 338 ### ITEMS- 233868 - Black oxide drill bit 1/16 12 pk - Package Size 12 pc - 410605 - Black oxide drill bit 1/2 6 pk - Package Size 6 pc - 246474 - Black oxide drill bit 1/4 12 pk - Package Size 12 pc - 234421 - Black oxide drill bit 1/8 12 pk - Package Size 12 pc - 241360 - Black oxide drill bit 13/64 12 pk - Package Size 12 pc - 233883 - Black oxide drill bit 3/32 12 pk - Package Size 12 pc - 383956 - Black oxide drill bit 3/8 6 pk - Package Size 6 pc - 273328 - Black oxide drill bit 5/16 6 pk - Package Size 6 pc - 241283 - Black oxide drill bit 5/32 12 pk - Package Size 12 pc - 410601 - Black oxide drill bit 7/16 6 pk - Package Size 6 pc - 241361 - Black oxide drill bit 7/32 12 pk - Package Size 12 pc - 238001 - Black oxide drill bit 9/64 12 pk - Package Size 12 pc",
  "tag_name": "HSS G Drill bit",
  "tag_description": "Premium HSS ground drill bit for drilling small holes in metal, DIN 338 compliant",
  "tag_source": "HOL: Products",
  "tag_author": "na",
  "tag_created_at": "na",
  "tag_ingestion_date": "2025-05-21T08:41:03.409282",
  "tag_categories_leaf": "Metal, wood and other material drill bits",
  "tag_categories_branch": "Home > Products > Tool inserts > Metal, wood and other material drill bits",
  "tag_item_numbers": "['233868', '410605', '246474', '234421', '241360', '233883', '383956', '273328', '241283', '410601', '241361', '238001']",
  "tag_related_files": "[]",
  "tag_sidelinks": "na",
  "tag_language": "en",
  "tag_country": "us",
  "tag_keywords": "na",
  "tag_page_number": "na",
  "tag_sku": "r1697732",
  "tag_file_type": "product_page",
  "tag_file_extension": "html"
}