{
  "tag_heading": "na",
  "tag_public_url": "https://www.hilti.com/c/CLS_POWER_TOOL_INSERT_7126/CLS_SAW_BLADES_7126/r16522852",
  "content": "Medium metal reciprocating saw blades (carbide) Ultimate carbide reciprocating saw blade for cutting 1/8 - 7/16 thick metal ### Categories: Home > Products > Tool inserts > Saw blades- - - ### FEATURES:Features Carbide-tipped teeth – essential if you want faster cuts and a longer lifespan when cutting tough metals like cast iron or stainless steel Ultimate cutting life – one Hilti carbide recip blade will outlast up to 50 Standard bimetal blades Smoother, steadier cutting – special tooth geometry and more teeth-per-inch help these blades to cut tougher materials with ease Faster cuts – engineered to cut through medium thick cast iron and stainless steel faster than any other Hilti metal cutting blades Low cost per cut – this extremely long-lasting blade can more than pay for itself in durability and fewer work stoppages for blade replacements Applications Faster cuts through tough metals – including cast iron, stainless steel and high-alloyed steel in 1/8 - 7/16 thickness Cutting structural steel ### TECHNICAL DATA: Product Class: Ultimate Shank: 1/2 in universal shank Teeth per inch: 10 Technical Data | Product Class | Ultimate | Teeth per inch | 10 | Blade features | Long life, Fast cut, Straight cut, Carbide tipped ### ITEMS- 2337433 - Recip saw blade SPX 6 10 TPI (3) - Package Size 3 pc - 2337435 - Recip saw blade SPX 9 10 TPI (3) - Package Size 3 pc - 2337437 - Recip saw blade SPX 12 10 TPI (3) - Package Size 3 pc",
  "tag_name": "Medium metal reciprocating saw blades (carbide)",
  "tag_description": "Ultimate carbide reciprocating saw blade for cutting 1/8 - 7/16 thick metal",
  "tag_source": "HOL: Products",
  "tag_author": "na",
  "tag_created_at": "na",
  "tag_ingestion_date": "2025-05-20T12:51:25.746905",
  "tag_categories_leaf": "Saw blades",
  "tag_categories_branch": "Home > Products > Tool inserts > Saw blades",
  "tag_item_numbers": "['2337433', '2337435', '2337437']",
  "tag_related_files": "[{'category': 'Documentation', 'url': 'https://productdata.hilti.com/APQ_HC_RAW/ASSET_DOC_19713274.pdf', 'description': 'Download SRB HNA Portfolio Overview_0622_g_en_2023'}]",
  "tag_sidelinks": "na",
  "tag_language": "en",
  "tag_country": "us",
  "tag_keywords": "na",
  "tag_page_number": "na",
  "tag_sku": "r16522852",
  "tag_file_type": "product_page",
  "tag_file_extension": "html"
}