{
  "tag_heading": "na",
  "tag_public_url": "https://www.hilti.com/c/CLS_MODULAR_SUPPORT_SYSTEM/CLS_STD_FIX_SUPPORT_SYS/r5426",
  "content": "MVA-ZP ventilation support Galvanized air duct bracket for fastening heavy ventilation ducts overhead ### Categories: Home > Products > Modular support systems > Standard fixings for support systems- - - ### FEATURES:Features Convenient solution for fastening ventilation ducts directly to the ceiling Scale for precise alignment and stand-off installation Movable cage – compensates for structural tolerances and allows repositioning to help avoid drilling into rebar Hole size/shape suitable for fastening to ducts using self-drilling screws (4.2, 4.8, 6.3), blind rivets 30 mm space between the threaded rod and the duct – for easier subsequent addition of insulation Applications Fastening rectangular air ducts to ceilings ### TECHNICAL DATA:Thread connection - M: M8, M10Noise reduction: 12 dB (A)Maximum load - F: 800 N Technical Data | Thread connection - M | M8, M10 | Noise reduction | 12 dB (A) | Maximum load - F | 800 N | Material composition | Angle: St1203 - DIN EN 10130, Plate: DC01-A-g - DIN EN 10130 | Surface finish | Indoor Coated - Electro galvanized | Environmental conditions | Dry indoor conditions (C1) Indoor with temporary condensation (C2) | Hardness Insulation Material | 40° ±5° Shore A | Temperature resistance | -40 - 230 °F ### ITEMS- 411499 - Air duct bracket MVA-ZP - Package Size 25 pc",
  "tag_name": "MVA-ZP ventilation support",
  "tag_description": "Galvanized air duct bracket for fastening heavy ventilation ducts overhead",
  "tag_source": "HOL: Products",
  "tag_author": "na",
  "tag_created_at": "na",
  "tag_ingestion_date": "2025-05-20T13:53:37.792233",
  "tag_categories_leaf": "Standard fixings for support systems",
  "tag_categories_branch": "Home > Products > Modular support systems > Standard fixings for support systems",
  "tag_item_numbers": "['411499']",
  "tag_related_files": "[{'category': 'Technical information', 'url': 'https://productdata.hilti.com/APQ_HC_RAW/ASSET_DOC_LOC_16475626.pdf', 'description': 'Download Wire Hanger System MW - Technical Guide'}, {'category': 'Brochure', 'url': 'https://productdata.hilti.com/APQ_HC_RAW/ASSET_DOC_LOC_16747294.pdf', 'description': 'Download Wire Hanger System Portfolio'}, {'category': 'Operating Instruction', 'url': 'https://productdata.hilti.com/APQ_HC_RAW/PUB_5626343_000.pdf', 'description': 'Download Operating Instruction MVA-ZC/-ZP'}]",
  "tag_sidelinks": "na",
  "tag_language": "en",
  "tag_country": "us",
  "tag_keywords": "na",
  "tag_page_number": "na",
  "tag_sku": "r5426",
  "tag_file_type": "product_page",
  "tag_file_extension": "html"
}