{
  "tag_heading": "na",
  "tag_public_url": "https://www.hilti.com/c/CLS_CONSTRCUT_CHEM_7132/CLS_ACC_FOR_CONSTRUCTION_CHEMICALS_7133/CLS_DISPENSING_ACCESSORIES_7133/311512",
  "content": "Plastic nozzle tip for CF and EX/DS ### Categories: Home > Products > Construction chemicals > Accessories for construction chemicals > Dispensing accessories ### FEATURES: ### TECHNICAL DATA: ### ITEMS- 311512 - Plastic nozzle tip for CF and EX/DS - Package Size 20 pc",
  "tag_name": "Plastic nozzle tip for CF and EX/DS",
  "tag_description": "",
  "tag_source": "HOL: Products",
  "tag_author": "na",
  "tag_created_at": "na",
  "tag_ingestion_date": "2025-05-21T13:31:11.057078",
  "tag_categories_leaf": "Dispensing accessories",
  "tag_categories_branch": "Home > Products > Construction chemicals > Accessories for construction chemicals > Dispensing accessories",
  "tag_item_numbers": "['311512']",
  "tag_related_files": "[]",
  "tag_sidelinks": "na",
  "tag_language": "en",
  "tag_country": "us",
  "tag_keywords": "na",
  "tag_page_number": "na",
  "tag_sku": "311512",
  "tag_file_type": "product_page",
  "tag_file_extension": "html"
}