{
  "tag_heading": "na",
  "tag_public_url": "https://www.hilti.com/c/CLS_FASTENER_7135/CLS_ACCESSORIES_FOR_TOOLS_7135/3675436",
  "content": "SDT Stand Up tool complete with (1) Extra SDT 9 Magazine ### Categories: Home > Products > Fasteners > Accessories for tools- - ### FEATURES:Features Higher-speed, higher-productivity method for driving decking screws using a compatible cordless screwdriver More comfortable, upright working position – less downtime due to operator fatigue Collated screw strips designed to provide trouble-free operation with reduced jamming Long, slender nosepiece – for easier access to deep and narrow profiles Height can be adjusted (80-130 cm) Applications Fastening overlapping metal sheets on insulated roofs Fastening metal sheets to bar joists in insulated roofs Fastening metal sheets to thin and thick metal beam substructures in insulated roofs Fastening edge reinforcement elements to metal sheets on insulated roofs ### TECHNICAL DATA: Screw length - min: 0.75 in Screw length - max: 1.57 in Technical Data | Screw length - min | 0.75 in | Screw length - max | 1.57 in ### ITEMS- 3675436 - SDT Stand Up tool complete with (1) Extra SDT 9 Magazine - Package Size 1 pc Package Contents: - 1x Integrated driver and setter SDT 5/16 - 1x Nose piece SDT 9-NP B black - 1x Nose piece SDT 9-NP R red - 1x Screw magazine - 1x Handle - 1x SDT 9-F Stand-up handle - 1x Screw magazine",
  "tag_name": "SDT Stand Up tool complete with (1) Extra SDT 9 Magazine",
  "tag_description": "",
  "tag_source": "HOL: Products",
  "tag_author": "na",
  "tag_created_at": "na",
  "tag_ingestion_date": "2025-05-20T14:57:51.769923",
  "tag_categories_leaf": "Accessories for tools",
  "tag_categories_branch": "Home > Products > Fasteners > Accessories for tools",
  "tag_item_numbers": "['3675436']",
  "tag_related_files": "[{'category': 'Brochure', 'url': 'https://productdata.hilti.com/APQ_HC_RAW/ASSET_DOC_LOC_16217793.pdf', 'description': 'Download Decking Application and Product Overview'}, {'category': 'Brochure', 'url': 'https://productdata.hilti.com/APQ_HC_RAW/ASSET_DOC_LOC_17382334.pdf', 'description': 'Download Decking Application and Product Overview'}, {'category': 'Brochure', 'url': 'https://productdata.hilti.com/APQ_HC_RAW/ASSET_DOC_LOC_17382380.pdf', 'description': 'Download Decking Application and Product Overview (CA-FR)'}, {'category': 'Operating Instruction', 'url': 'https://productdata.hilti.com/APQ_HC_RAW/PUB_5451942_000.pdf', 'description': 'Download Operating Instruction SDT 9'}]",
  "tag_sidelinks": "na",
  "tag_language": "en",
  "tag_country": "us",
  "tag_keywords": "na",
  "tag_page_number": "na",
  "tag_sku": "3675436",
  "tag_file_type": "product_page",
  "tag_file_extension": "html"
}